{
  "page_ark": "d73s33-006",
  "ark": "d73s33",
  "page": 6,
  "name": "MESNIL BLANC DE BLANCS",
  "year_published": 1967,
  "vintage": 1961,
  "type": "wine",
  "color": "white",
  "country": null,
  "section": null,
  "bottle_type": null,
  "perprice": 6.98,
  "caseprice": null,
  "bbox": "{\"type\":\"Polygon\",\"coordinates\":[[[202,-3299],[202,-3252],[1785,-3252],[1785,-3299],[202,-3299]]]}",
  "title": "Your Own New Year's Party 1967",
  "publisher": "Sherry Wine & Spirits Co.,Inc.",
  "publication_date": 1967
}
{
  "page_ark": "d73s33-006",
  "ark": "d73s33",
  "page": 6,
  "name": "155 AYALA GOLD LABEL BRUT",
  "year_published": 1967,
  "vintage": 1961,
  "type": "wine",
  "color": null,
  "country": "France",
  "section": null,
  "bottle_type": null,
  "perprice": 5.49,
  "caseprice": null,
  "bbox": "{\"type\":\"Polygon\",\"coordinates\":[[[202,-2894],[202,-2845],[1776,-2845],[1776,-2894],[202,-2894]]]}",
  "title": "Your Own New Year's Party 1967",
  "publisher": "Sherry Wine & Spirits Co.,Inc.",
  "publication_date": 1967
}
{
  "page_ark": "d73s33-007",
  "ark": "d73s33",
  "page": 7,
  "name": "Royal Brown Oloroso",
  "year_published": 1967,
  "vintage": null,
  "type": "wine",
  "color": null,
  "country": null,
  "section": null,
  "bottle_type": null,
  "perprice": 21.95,
  "caseprice": null,
  "bbox": "{\"type\":\"Polygon\",\"coordinates\":[[[221,-3347],[221,-3297],[1931,-3297],[1931,-3347],[221,-3347]]]}",
  "title": "Your Own New Year's Party 1967",
  "publisher": "Sherry Wine & Spirits Co.,Inc.",
  "publication_date": 1967
}
{
  "page_ark": "d73s33-005",
  "ark": "d73s33",
  "page": 5,
  "name": "most periectonistic (0) $0000 990000 YVSIYD Bual existence costly KEAS",
  "year_published": 1967,
  "vintage": 1897,
  "type": "wine",
  "color": null,
  "country": null,
  "section": null,
  "bottle_type": null,
  "perprice": 16,
  "caseprice": null,
  "bbox": "{\"type\":\"Polygon\",\"coordinates\":[[[169,-5320],[169,-5254],[3681,-5254],[3681,-5320],[169,-5320]]]}",
  "title": "Your Own New Year's Party 1967",
  "publisher": "Sherry Wine & Spirits Co.,Inc.",
  "publication_date": 1967
}
{
  "page_ark": "d73s33-005",
  "ark": "d73s33",
  "page": 5,
  "name": "New Yedr Sercial",
  "year_published": 1967,
  "vintage": 1898,
  "type": "wine",
  "color": null,
  "country": "US",
  "section": null,
  "bottle_type": null,
  "perprice": 16,
  "caseprice": null,
  "bbox": "{\"type\":\"Polygon\",\"coordinates\":[[[169,-5450],[169,-5383],[3681,-5383],[3681,-5450],[169,-5450]]]}",
  "title": "Your Own New Year's Party 1967",
  "publisher": "Sherry Wine & Spirits Co.,Inc.",
  "publication_date": 1967
}
{
  "page_ark": "d73s33-006",
  "ark": "d73s33",
  "page": 6,
  "name": "SAINT MICHEL BRUT",
  "year_published": 1967,
  "vintage": null,
  "type": "wine",
  "color": null,
  "country": null,
  "section": null,
  "bottle_type": null,
  "perprice": 2.79,
  "caseprice": 31.5,
  "bbox": "{\"type\":\"Polygon\",\"coordinates\":[[[392.3,-1338],[392.3,-1273],[2053,-1273],[2053,-1338],[392.3,-1338]]]}",
  "title": "Your Own New Year's Party 1967",
  "publisher": "Sherry Wine & Spirits Co.,Inc.",
  "publication_date": 1967
}
{
  "page_ark": "d73s33-006",
  "ark": "d73s33",
  "page": 6,
  "name": "CHATEAU HANTEILLAN",
  "year_published": 1967,
  "vintage": 1962,
  "type": "wine",
  "color": null,
  "country": "France",
  "section": null,
  "bottle_type": null,
  "perprice": 1.99,
  "caseprice": null,
  "bbox": "{\"type\":\"Polygon\",\"coordinates\":[[[2109.5,-4345],[2109.5,-4297],[3385,-4297],[3385,-4345],[2109.5,-4345]]]}",
  "title": "Your Own New Year's Party 1967",
  "publisher": "Sherry Wine & Spirits Co.,Inc.",
  "publication_date": 1967
}
{
  "page_ark": "d73s33-006",
  "ark": "d73s33",
  "page": 6,
  "name": "DOM PERIGNON MAGNUM",
  "year_published": 1967,
  "vintage": null,
  "type": "wine",
  "color": null,
  "country": null,
  "section": null,
  "bottle_type": null,
  "perprice": 27,
  "caseprice": 145.8,
  "bbox": "{\"type\":\"Polygon\",\"coordinates\":[[[392.3,-4789],[392.3,-4741],[2052,-4741],[2052,-4789],[392.3,-4789]]]}",
  "title": "Your Own New Year's Party 1967",
  "publisher": "Sherry Wine & Spirits Co.,Inc.",
  "publication_date": 1967
}
{
  "page_ark": "d73s33-007",
  "ark": "d73s33",
  "page": 7,
  "name": "Fino Palma",
  "year_published": 1967,
  "vintage": null,
  "type": "wine",
  "color": null,
  "country": null,
  "section": null,
  "bottle_type": null,
  "perprice": 19.75,
  "caseprice": null,
  "bbox": "{\"type\":\"Polygon\",\"coordinates\":[[[221,-3275],[221,-3223],[1911,-3223],[1911,-3275],[221,-3275]]]}",
  "title": "Your Own New Year's Party 1967",
  "publisher": "Sherry Wine & Spirits Co.,Inc.",
  "publication_date": 1967
}
{
  "page_ark": "d73s33-007",
  "ark": "d73s33",
  "page": 7,
  "name": "Amontillado Fino",
  "year_published": 1967,
  "vintage": null,
  "type": "wine",
  "color": null,
  "country": "Italy",
  "section": null,
  "bottle_type": null,
  "perprice": 97.5,
  "caseprice": null,
  "bbox": "{\"type\":\"Polygon\",\"coordinates\":[[[221,-3418],[221,-3361],[1923,-3361],[1923,-3418],[221,-3418]]]}",
  "title": "Your Own New Year's Party 1967",
  "publisher": "Sherry Wine & Spirits Co.,Inc.",
  "publication_date": 1967
}
{
  "page_ark": "d73s33-006",
  "ark": "d73s33",
  "page": 6,
  "name": "BEAJOLAIS VILLAGES",
  "year_published": 1967,
  "vintage": 1966,
  "type": "wine",
  "color": null,
  "country": "France",
  "section": null,
  "bottle_type": null,
  "perprice": 2.19,
  "caseprice": null,
  "bbox": "{\"type\":\"Polygon\",\"coordinates\":[[[2116.5,-4813],[2116.5,-4767],[3369,-4767],[3369,-4813],[2116.5,-4813]]]}",
  "title": "Your Own New Year's Party 1967",
  "publisher": "Sherry Wine & Spirits Co.,Inc.",
  "publication_date": 1967
}
{
  "page_ark": "d73s33-007",
  "ark": "d73s33",
  "page": 7,
  "name": "531 CHAT ROC SAINT MICHEL",
  "year_published": 1967,
  "vintage": 1862,
  "type": "wine",
  "color": null,
  "country": null,
  "section": null,
  "bottle_type": null,
  "perprice": 2.49,
  "caseprice": 26.9,
  "bbox": "{\"type\":\"Polygon\",\"coordinates\":[[[221,-1041],[221,-991],[1949,-991],[1949,-1041],[221,-1041]]]}",
  "title": "Your Own New Year's Party 1967",
  "publisher": "Sherry Wine & Spirits Co.,Inc.",
  "publication_date": 1967
}
{
  "page_ark": "d73s33-006",
  "ark": "d73s33",
  "page": 6,
  "name": "AAV ILANAVALe MARCEL PERE BRUT",
  "year_published": 1967,
  "vintage": 1961,
  "type": "wine",
  "color": null,
  "country": null,
  "section": null,
  "bottle_type": null,
  "perprice": 4.79,
  "caseprice": 52.75,
  "bbox": "{\"type\":\"Polygon\",\"coordinates\":[[[392.3,-2081],[392.3,-2025],[2066,-2025],[2066,-2081],[392.3,-2081]]]}",
  "title": "Your Own New Year's Party 1967",
  "publisher": "Sherry Wine & Spirits Co.,Inc.",
  "publication_date": 1967
}
{
  "page_ark": "d73s33-006",
  "ark": "d73s33",
  "page": 6,
  "name": "TAITTINGER BLANC DE BLA}",
  "year_published": 1967,
  "vintage": null,
  "type": "wine",
  "color": "white",
  "country": "France",
  "section": null,
  "bottle_type": null,
  "perprice": 13.69,
  "caseprice": null,
  "bbox": "{\"type\":\"Polygon\",\"coordinates\":[[[392.3,-4451],[392.3,-4388],[1728,-4388],[1728,-4451],[392.3,-4451]]]}",
  "title": "Your Own New Year's Party 1967",
  "publisher": "Sherry Wine & Spirits Co.,Inc.",
  "publication_date": 1967
}
{
  "page_ark": "d73s33-007",
  "ark": "d73s33",
  "page": 7,
  "name": "CHAT CLOSE RENE",
  "year_published": 1967,
  "vintage": 1961,
  "type": "wine",
  "color": null,
  "country": null,
  "section": null,
  "bottle_type": null,
  "perprice": 3.49,
  "caseprice": 37.7,
  "bbox": "{\"type\":\"Polygon\",\"coordinates\":[[[221,-1471],[221,-1413],[1985,-1413],[1985,-1471],[221,-1471]]]}",
  "title": "Your Own New Year's Party 1967",
  "publisher": "Sherry Wine & Spirits Co.,Inc.",
  "publication_date": 1967
}
{
  "page_ark": "d73s33-006",
  "ark": "d73s33",
  "page": 6,
  "name": "",
  "year_published": 1967,
  "vintage": null,
  "type": "wine",
  "color": null,
  "country": null,
  "section": null,
  "bottle_type": null,
  "perprice": 129.06,
  "caseprice": null,
  "bbox": "{\"type\":\"Polygon\",\"coordinates\":[[[392.3,-3907],[392.3,-3879.5],[2054,-3879.5],[2054,-3907],[392.3,-3907]]]}",
  "title": "Your Own New Year's Party 1967",
  "publisher": "Sherry Wine & Spirits Co.,Inc.",
  "publication_date": 1967
}
{
  "page_ark": "d73s33-007",
  "ark": "d73s33",
  "page": 7,
  "name": "Golden Cream",
  "year_published": 1967,
  "vintage": null,
  "type": "wine",
  "color": null,
  "country": "US",
  "section": null,
  "bottle_type": null,
  "perprice": 33.98,
  "caseprice": null,
  "bbox": "{\"type\":\"Polygon\",\"coordinates\":[[[221,-3487],[221,-3430],[2142,-3430],[2142,-3487],[221,-3487]]]}",
  "title": "Your Own New Year's Party 1967",
  "publisher": "Sherry Wine & Spirits Co.,Inc.",
  "publication_date": 1967
}
{
  "page_ark": "d73s33-006",
  "ark": "d73s33",
  "page": 6,
  "name": "CABERNET SAUVIGNON",
  "year_published": 1967,
  "vintage": null,
  "type": "wine",
  "color": null,
  "country": null,
  "section": null,
  "bottle_type": null,
  "perprice": 1.52,
  "caseprice": null,
  "bbox": "{\"type\":\"Polygon\",\"coordinates\":[[[2130.5,-3981],[2130.5,-3922],[3348,-3922],[3348,-3981],[2130.5,-3981]]]}",
  "title": "Your Own New Year's Party 1967",
  "publisher": "Sherry Wine & Spirits Co.,Inc.",
  "publication_date": 1967
}
{
  "page_ark": "d73s33-007",
  "ark": "d73s33",
  "page": 7,
  "name": "CHATEAU JACQUES",
  "year_published": 1967,
  "vintage": 1953,
  "type": "wine",
  "color": null,
  "country": null,
  "section": null,
  "bottle_type": null,
  "perprice": 3.99,
  "caseprice": 43.93,
  "bbox": "{\"type\":\"Polygon\",\"coordinates\":[[[221,-2043],[221,-1981],[2003,-1981],[2003,-2043],[221,-2043]]]}",
  "title": "Your Own New Year's Party 1967",
  "publisher": "Sherry Wine & Spirits Co.,Inc.",
  "publication_date": 1967
}
{
  "page_ark": "d73s33-006",
  "ark": "d73s33",
  "page": 6,
  "name": "SEBASTIANI BRUT (Calif)",
  "year_published": 1967,
  "vintage": null,
  "type": "wine",
  "color": null,
  "country": "US",
  "section": null,
  "bottle_type": null,
  "perprice": 3.59,
  "caseprice": 38.75,
  "bbox": "{\"type\":\"Polygon\",\"coordinates\":[[[394.5,-1687],[394.5,-1620],[2062,-1620],[2062,-1687],[394.5,-1687]]]}",
  "title": "Your Own New Year's Party 1967",
  "publisher": "Sherry Wine & Spirits Co.,Inc.",
  "publication_date": 1967
}
{
  "page_ark": "d73s33-006",
  "ark": "d73s33",
  "page": 6,
  "name": "AYALA GOLD LABEL BRUT",
  "year_published": 1967,
  "vintage": 1961,
  "type": "wine",
  "color": null,
  "country": "France",
  "section": null,
  "bottle_type": null,
  "perprice": 5.49,
  "caseprice": 60.5,
  "bbox": "{\"type\":\"Polygon\",\"coordinates\":[[[393.5,-2906],[393.5,-2837],[2059,-2837],[2059,-2906],[393.5,-2906]]]}",
  "title": "Your Own New Year's Party 1967",
  "publisher": "Sherry Wine & Spirits Co.,Inc.",
  "publication_date": 1967
}
{
  "page_ark": "d73s33-006",
  "ark": "d73s33",
  "page": 6,
  "name": "KORBEL BRUT (Calif",
  "year_published": 1967,
  "vintage": null,
  "type": "wine",
  "color": null,
  "country": "US",
  "section": null,
  "bottle_type": null,
  "perprice": 3.89,
  "caseprice": 4.99,
  "bbox": "{\"type\":\"Polygon\",\"coordinates\":[[[396.5,-2433],[396.5,-2375],[2060,-2375],[2060,-2433],[396.5,-2433]]]}",
  "title": "Your Own New Year's Party 1967",
  "publisher": "Sherry Wine & Spirits Co.,Inc.",
  "publication_date": 1967
}
