{
  "page_ark": "d7k30d-001",
  "ark": "d7k30d",
  "page": 1,
  "name": "201 POMMARD RUGIENS",
  "year_published": 1961,
  "vintage": 1959,
  "type": "wine",
  "color": null,
  "country": "France",
  "section": null,
  "bottle_type": null,
  "perprice": 3.99,
  "caseprice": 43.95,
  "bbox": "{\"type\":\"Polygon\",\"coordinates\":[[[1986.7,-3321],[1986.7,-3270],[3628,-3270],[3628,-3321],[1986.7,-3321]]]}",
  "title": "Exciting Wine News from Burgundy 1961",
  "publisher": "Sherry Wine & Spirits Co.,Inc.",
  "publication_date": 1961
}
{
  "page_ark": "d7k30d-002",
  "ark": "d7k30d",
  "page": 2,
  "name": "CHATEAU PAVIE (Saint Emilion)",
  "year_published": 1961,
  "vintage": null,
  "type": "wine",
  "color": null,
  "country": "France",
  "section": null,
  "bottle_type": null,
  "perprice": 31,
  "caseprice": null,
  "bbox": "{\"type\":\"Polygon\",\"coordinates\":[[[244,-4467],[244,-4434],[1872,-4434],[1872,-4467],[244,-4467]]]}",
  "title": "Exciting Wine News from Burgundy 1961",
  "publisher": "Sherry Wine & Spirits Co.,Inc.",
  "publication_date": 1961
}
{
  "page_ark": "d7k30d-002",
  "ark": "d7k30d",
  "page": 2,
  "name": "CHATEAU LYNCH BAGES (Pauillac) PRO DRT",
  "year_published": 1961,
  "vintage": null,
  "type": "wine",
  "color": null,
  "country": "France",
  "section": null,
  "bottle_type": null,
  "perprice": 39.5,
  "caseprice": null,
  "bbox": "{\"type\":\"Polygon\",\"coordinates\":[[[1963,-1786],[1963,-1755],[3602,-1755],[3602,-1786],[1963,-1786]]]}",
  "title": "Exciting Wine News from Burgundy 1961",
  "publisher": "Sherry Wine & Spirits Co.,Inc.",
  "publication_date": 1961
}
{
  "page_ark": "d7k30d-003",
  "ark": "d7k30d",
  "page": 3,
  "name": "RICHEBOURG",
  "year_published": 1961,
  "vintage": null,
  "type": "wine",
  "color": null,
  "country": null,
  "section": null,
  "bottle_type": null,
  "perprice": 66,
  "caseprice": null,
  "bbox": "{\"type\":\"Polygon\",\"coordinates\":[[[341.666666666667,-3318],[341.666666666667,-3275],[1848,-3275],[1848,-3318],[341.666666666667,-3318]]]}",
  "title": "Exciting Wine News from Burgundy 1961",
  "publisher": "Sherry Wine & Spirits Co.,Inc.",
  "publication_date": 1961
}
{
  "page_ark": "d7k30d-002",
  "ark": "d7k30d",
  "page": 2,
  "name": "Not Lascases CHATEAU (Saint Estephe) taetsshasstissessors",
  "year_published": 1961,
  "vintage": null,
  "type": "wine",
  "color": "rose",
  "country": null,
  "section": null,
  "bottle_type": null,
  "perprice": 42.5,
  "caseprice": null,
  "bbox": "{\"type\":\"Polygon\",\"coordinates\":[[[1961,-3042],[1961,-3000],[3606,-3000],[3606,-3042],[1961,-3042]]]}",
  "title": "Exciting Wine News from Burgundy 1961",
  "publisher": "Sherry Wine & Spirits Co.,Inc.",
  "publication_date": 1961
}
{
  "page_ark": "d7k30d-002",
  "ark": "d7k30d",
  "page": 2,
  "name": "CHATEAU COS (Saint Estephe)",
  "year_published": 1961,
  "vintage": null,
  "type": "wine",
  "color": null,
  "country": null,
  "section": null,
  "bottle_type": null,
  "perprice": 45,
  "caseprice": null,
  "bbox": "{\"type\":\"Polygon\",\"coordinates\":[[[1961,-3425],[1961,-3384],[3610,-3384],[3610,-3425],[1961,-3425]]]}",
  "title": "Exciting Wine News from Burgundy 1961",
  "publisher": "Sherry Wine & Spirits Co.,Inc.",
  "publication_date": 1961
}
{
  "page_ark": "d7k30d-002",
  "ark": "d7k30d",
  "page": 2,
  "name": "best LAFITE ROTHSCHILD (Pauillac)",
  "year_published": 1961,
  "vintage": null,
  "type": "wine",
  "color": null,
  "country": "France",
  "section": null,
  "bottle_type": null,
  "perprice": 87.5,
  "caseprice": null,
  "bbox": "{\"type\":\"Polygon\",\"coordinates\":[[[1961,-4733],[1961,-4690],[3611,-4690],[3611,-4733],[1961,-4733]]]}",
  "title": "Exciting Wine News from Burgundy 1961",
  "publisher": "Sherry Wine & Spirits Co.,Inc.",
  "publication_date": 1961
}
{
  "page_ark": "d7k30d-002",
  "ark": "d7k30d",
  "page": 2,
  "name": "CHATEAU DUCRU BEAUCAILLOU (Saint Julier",
  "year_published": 1961,
  "vintage": null,
  "type": "wine",
  "color": null,
  "country": "France",
  "section": null,
  "bottle_type": null,
  "perprice": 29.5,
  "caseprice": null,
  "bbox": "{\"type\":\"Polygon\",\"coordinates\":[[[1961,-2087],[1961,-2055],[3603,-2055],[3603,-2087],[1961,-2087]]]}",
  "title": "Exciting Wine News from Burgundy 1961",
  "publisher": "Sherry Wine & Spirits Co.,Inc.",
  "publication_date": 1961
}
{
  "page_ark": "d7k30d-002",
  "ark": "d7k30d",
  "page": 2,
  "name": "CHATEAU LASCOMBES (Margaux)",
  "year_published": 1961,
  "vintage": null,
  "type": "wine",
  "color": null,
  "country": "France",
  "section": null,
  "bottle_type": null,
  "perprice": 41,
  "caseprice": null,
  "bbox": "{\"type\":\"Polygon\",\"coordinates\":[[[1962,-2385],[1962,-2352],[3603,-2352],[3603,-2385],[1962,-2385]]]}",
  "title": "Exciting Wine News from Burgundy 1961",
  "publisher": "Sherry Wine & Spirits Co.,Inc.",
  "publication_date": 1961
}
{
  "page_ark": "d7k30d-003",
  "ark": "d7k30d",
  "page": 3,
  "name": "CHARMES CHAMBERTIN",
  "year_published": 1961,
  "vintage": null,
  "type": "wine",
  "color": null,
  "country": "France",
  "section": null,
  "bottle_type": null,
  "perprice": 5.49,
  "caseprice": null,
  "bbox": "{\"type\":\"Polygon\",\"coordinates\":[[[243.5,-2659],[243.5,-2617],[1550,-2617],[1550,-2659],[243.5,-2659]]]}",
  "title": "Exciting Wine News from Burgundy 1961",
  "publisher": "Sherry Wine & Spirits Co.,Inc.",
  "publication_date": 1961
}
{
  "page_ark": "d7k30d-001",
  "ark": "d7k30d",
  "page": 1,
  "name": "Gold Medals 484 ECHEZEAUX",
  "year_published": 1961,
  "vintage": null,
  "type": "wine",
  "color": null,
  "country": null,
  "section": null,
  "bottle_type": null,
  "perprice": 3.99,
  "caseprice": 43.95,
  "bbox": "{\"type\":\"Polygon\",\"coordinates\":[[[1986.7,-2716],[1986.7,-2672],[3609,-2672],[3609,-2716],[1986.7,-2716]]]}",
  "title": "Exciting Wine News from Burgundy 1961",
  "publisher": "Sherry Wine & Spirits Co.,Inc.",
  "publication_date": 1961
}
{
  "page_ark": "d7k30d-002",
  "ark": "d7k30d",
  "page": 2,
  "name": "CHATEAU LEOVILLE POYFERRE",
  "year_published": 1961,
  "vintage": null,
  "type": "wine",
  "color": null,
  "country": "France",
  "section": null,
  "bottle_type": null,
  "perprice": 41.5,
  "caseprice": null,
  "bbox": "{\"type\":\"Polygon\",\"coordinates\":[[[1961,-2916],[1961,-2874],[3604,-2874],[3604,-2916],[1961,-2916]]]}",
  "title": "Exciting Wine News from Burgundy 1961",
  "publisher": "Sherry Wine & Spirits Co.,Inc.",
  "publication_date": 1961
}
{
  "page_ark": "d7k30d-003",
  "ark": "d7k30d",
  "page": 3,
  "name": "MONTRACHET eestmaonedite",
  "year_published": 1961,
  "vintage": null,
  "type": "wine",
  "color": null,
  "country": "France",
  "section": null,
  "bottle_type": null,
  "perprice": 7.1,
  "caseprice": 78,
  "bbox": "{\"type\":\"Polygon\",\"coordinates\":[[[1951.5,-4477],[1951.5,-4440],[3583,-4440],[3583,-4477],[1951.5,-4477]]]}",
  "title": "Exciting Wine News from Burgundy 1961",
  "publisher": "Sherry Wine & Spirits Co.,Inc.",
  "publication_date": 1961
}
{
  "page_ark": "d7k30d-001",
  "ark": "d7k30d",
  "page": 1,
  "name": "demands",
  "year_published": 1961,
  "vintage": 1959,
  "type": "wine",
  "color": null,
  "country": null,
  "section": null,
  "bottle_type": null,
  "perprice": 19.59,
  "caseprice": null,
  "bbox": "{\"type\":\"Polygon\",\"coordinates\":[[[223.666666666667,-3045],[223.666666666667,-3002],[1528,-3002],[1528,-3045],[223.666666666667,-3045]]]}",
  "title": "Exciting Wine News from Burgundy 1961",
  "publisher": "Sherry Wine & Spirits Co.,Inc.",
  "publication_date": 1961
}
{
  "page_ark": "d7k30d-001",
  "ark": "d7k30d",
  "page": 1,
  "name": "271 CLOS DE TART",
  "year_published": 1961,
  "vintage": null,
  "type": "wine",
  "color": null,
  "country": "France",
  "section": null,
  "bottle_type": null,
  "perprice": 4.19,
  "caseprice": 46.25,
  "bbox": "{\"type\":\"Polygon\",\"coordinates\":[[[1986.7,-4321],[1986.7,-4284],[3608,-4284],[3608,-4321],[1986.7,-4321]]]}",
  "title": "Exciting Wine News from Burgundy 1961",
  "publisher": "Sherry Wine & Spirits Co.,Inc.",
  "publication_date": 1961
}
{
  "page_ark": "d7k30d-002",
  "ark": "d7k30d",
  "page": 2,
  "name": "CHATEAU CAPBERN (Saint Estephe)",
  "year_published": 1961,
  "vintage": null,
  "type": "wine",
  "color": null,
  "country": "France",
  "section": null,
  "bottle_type": null,
  "perprice": 29.5,
  "caseprice": null,
  "bbox": "{\"type\":\"Polygon\",\"coordinates\":[[[239,-4342],[239,-4309],[1871,-4309],[1871,-4342],[239,-4342]]]}",
  "title": "Exciting Wine News from Burgundy 1961",
  "publisher": "Sherry Wine & Spirits Co.,Inc.",
  "publication_date": 1961
}
{
  "page_ark": "d7k30d-002",
  "ark": "d7k30d",
  "page": 2,
  "name": "Distinguished depth Slow CHATEAU PETRUS (Pomerol)",
  "year_published": 1961,
  "vintage": null,
  "type": "wine",
  "color": null,
  "country": "France",
  "section": null,
  "bottle_type": null,
  "perprice": 75,
  "caseprice": null,
  "bbox": "{\"type\":\"Polygon\",\"coordinates\":[[[1961,-3806],[1961,-3764],[3618,-3764],[3618,-3806],[1961,-3806]]]}",
  "title": "Exciting Wine News from Burgundy 1961",
  "publisher": "Sherry Wine & Spirits Co.,Inc.",
  "publication_date": 1961
}
{
  "page_ark": "d7k30d-002",
  "ark": "d7k30d",
  "page": 2,
  "name": "Hes IER delicate CHATEAU CHEVAL BLANC (Saint Emilion)",
  "year_published": 1961,
  "vintage": null,
  "type": "wine",
  "color": "white",
  "country": "France",
  "section": null,
  "bottle_type": null,
  "perprice": 85,
  "caseprice": null,
  "bbox": "{\"type\":\"Polygon\",\"coordinates\":[[[1961,-4267],[1961,-4225],[3612,-4225],[3612,-4267],[1961,-4267]]]}",
  "title": "Exciting Wine News from Burgundy 1961",
  "publisher": "Sherry Wine & Spirits Co.,Inc.",
  "publication_date": 1961
}
{
  "page_ark": "d7k30d-003",
  "ark": "d7k30d",
  "page": 3,
  "name": "France Here indeed",
  "year_published": 1961,
  "vintage": null,
  "type": "wine",
  "color": null,
  "country": "US",
  "section": null,
  "bottle_type": null,
  "perprice": 19.59,
  "caseprice": null,
  "bbox": "{\"type\":\"Polygon\",\"coordinates\":[[[1953.1,-2392],[1953.1,-2357],[3253,-2357],[3253,-2392],[1953.1,-2392]]]}",
  "title": "Exciting Wine News from Burgundy 1961",
  "publisher": "Sherry Wine & Spirits Co.,Inc.",
  "publication_date": 1961
}
{
  "page_ark": "d7k30d-003",
  "ark": "d7k30d",
  "page": 3,
  "name": "BEAUJOLAIS BLANC",
  "year_published": 1961,
  "vintage": 1959,
  "type": "wine",
  "color": "white",
  "country": "France",
  "section": null,
  "bottle_type": null,
  "perprice": 1.99,
  "caseprice": null,
  "bbox": "{\"type\":\"Polygon\",\"coordinates\":[[[232.5,-4683],[232.5,-4643],[1561,-4643],[1561,-4683],[232.5,-4683]]]}",
  "title": "Exciting Wine News from Burgundy 1961",
  "publisher": "Sherry Wine & Spirits Co.,Inc.",
  "publication_date": 1961
}
{
  "page_ark": "d7k30d-001",
  "ark": "d7k30d",
  "page": 1,
  "name": "VOUGEOT DE CLOS 805",
  "year_published": 1961,
  "vintage": null,
  "type": "wine",
  "color": null,
  "country": "France",
  "section": null,
  "bottle_type": null,
  "perprice": 4.59,
  "caseprice": 49.75,
  "bbox": "{\"type\":\"Polygon\",\"coordinates\":[[[1986.7,-4737],[1986.7,-4699],[3610,-4699],[3610,-4737],[1986.7,-4737]]]}",
  "title": "Exciting Wine News from Burgundy 1961",
  "publisher": "Sherry Wine & Spirits Co.,Inc.",
  "publication_date": 1961
}
{
  "page_ark": "d7k30d-002",
  "ark": "d7k30d",
  "page": 2,
  "name": "CHATEAU MEYNEY (Saint Estephe)",
  "year_published": 1961,
  "vintage": null,
  "type": "wine",
  "color": null,
  "country": "France",
  "section": null,
  "bottle_type": null,
  "perprice": 32.5,
  "caseprice": null,
  "bbox": "{\"type\":\"Polygon\",\"coordinates\":[[[250,-4912],[250,-4881],[1877,-4881],[1877,-4912],[250,-4912]]]}",
  "title": "Exciting Wine News from Burgundy 1961",
  "publisher": "Sherry Wine & Spirits Co.,Inc.",
  "publication_date": 1961
}
{
  "page_ark": "d7k30d-002",
  "ark": "d7k30d",
  "page": 2,
  "name": "CHATEAU TIMBERLAY (Saint de Cubzac)",
  "year_published": 1961,
  "vintage": null,
  "type": "wine",
  "color": null,
  "country": "France",
  "section": null,
  "bottle_type": null,
  "perprice": 21.5,
  "caseprice": null,
  "bbox": "{\"type\":\"Polygon\",\"coordinates\":[[[239,-3335],[239,-3297],[1866,-3297],[1866,-3335],[239,-3335]]]}",
  "title": "Exciting Wine News from Burgundy 1961",
  "publisher": "Sherry Wine & Spirits Co.,Inc.",
  "publication_date": 1961
}
{
  "page_ark": "d7k30d-002",
  "ark": "d7k30d",
  "page": 2,
  "name": "CHATEAU GRAND PUY DUCASSE",
  "year_published": 1961,
  "vintage": null,
  "type": "wine",
  "color": null,
  "country": "France",
  "section": null,
  "bottle_type": null,
  "perprice": 31,
  "caseprice": null,
  "bbox": "{\"type\":\"Polygon\",\"coordinates\":[[[239,-4546],[239,-4514],[1874,-4514],[1874,-4546],[239,-4546]]]}",
  "title": "Exciting Wine News from Burgundy 1961",
  "publisher": "Sherry Wine & Spirits Co.,Inc.",
  "publication_date": 1961
}
{
  "page_ark": "d7k30d-002",
  "ark": "d7k30d",
  "page": 2,
  "name": "ATE 705 BRANAIRE DUCRU (Saint Julien)",
  "year_published": 1961,
  "vintage": null,
  "type": "wine",
  "color": null,
  "country": "US",
  "section": null,
  "bottle_type": null,
  "perprice": 32,
  "caseprice": null,
  "bbox": "{\"type\":\"Polygon\",\"coordinates\":[[[248,-4752],[248,-4719],[1875,-4719],[1875,-4752],[248,-4752]]]}",
  "title": "Exciting Wine News from Burgundy 1961",
  "publisher": "Sherry Wine & Spirits Co.,Inc.",
  "publication_date": 1961
}
{
  "page_ark": "d7k30d-002",
  "ark": "d7k30d",
  "page": 2,
  "name": "CHATEAU PALMER (Margaux)",
  "year_published": 1961,
  "vintage": null,
  "type": "wine",
  "color": null,
  "country": "France",
  "section": null,
  "bottle_type": null,
  "perprice": 45,
  "caseprice": null,
  "bbox": "{\"type\":\"Polygon\",\"coordinates\":[[[1962,-3296],[1962,-3257],[3609,-3257],[3609,-3296],[1962,-3296]]]}",
  "title": "Exciting Wine News from Burgundy 1961",
  "publisher": "Sherry Wine & Spirits Co.,Inc.",
  "publication_date": 1961
}
{
  "page_ark": "d7k30d-002",
  "ark": "d7k30d",
  "page": 2,
  "name": "Production CHATEAU MOUTON ROTHSCHILD (Pauillac",
  "year_published": 1961,
  "vintage": null,
  "type": "wine",
  "color": null,
  "country": "France",
  "section": null,
  "bottle_type": null,
  "perprice": 87.5,
  "caseprice": null,
  "bbox": "{\"type\":\"Polygon\",\"coordinates\":[[[1961,-4562],[1961,-4520],[3612,-4520],[3612,-4562],[1961,-4562]]]}",
  "title": "Exciting Wine News from Burgundy 1961",
  "publisher": "Sherry Wine & Spirits Co.,Inc.",
  "publication_date": 1961
}
{
  "page_ark": "d7k30d-003",
  "ark": "d7k30d",
  "page": 3,
  "name": "PULIGNY MONTRACHET LES PUCELLES",
  "year_published": 1961,
  "vintage": null,
  "type": "wine",
  "color": null,
  "country": "France",
  "section": null,
  "bottle_type": null,
  "perprice": 3.99,
  "caseprice": 43.95,
  "bbox": "{\"type\":\"Polygon\",\"coordinates\":[[[1961.5,-2607],[1961.5,-2564],[3576,-2564],[3576,-2607],[1961.5,-2607]]]}",
  "title": "Exciting Wine News from Burgundy 1961",
  "publisher": "Sherry Wine & Spirits Co.,Inc.",
  "publication_date": 1961
}
{
  "page_ark": "d7k30d-003",
  "ark": "d7k30d",
  "page": 3,
  "name": "CHASSAGNE MONTRACHET MORGEOT",
  "year_published": 1961,
  "vintage": null,
  "type": "wine",
  "color": null,
  "country": "France",
  "section": null,
  "bottle_type": null,
  "perprice": 3.99,
  "caseprice": 43.95,
  "bbox": "{\"type\":\"Polygon\",\"coordinates\":[[[1953.1,-3026],[1953.1,-2986],[3578,-2986],[3578,-3026],[1953.1,-3026]]]}",
  "title": "Exciting Wine News from Burgundy 1961",
  "publisher": "Sherry Wine & Spirits Co.,Inc.",
  "publication_date": 1961
}
{
  "page_ark": "d7k30d-001",
  "ark": "d7k30d",
  "page": 1,
  "name": "CHATEAU DE MONTHELIE",
  "year_published": 1961,
  "vintage": null,
  "type": "wine",
  "color": null,
  "country": "France",
  "section": null,
  "bottle_type": null,
  "perprice": 2.79,
  "caseprice": 30.75,
  "bbox": "{\"type\":\"Polygon\",\"coordinates\":[[[223.666666666667,-4324],[223.666666666667,-4281],[1859,-4281],[1859,-4324],[223.666666666667,-4324]]]}",
  "title": "Exciting Wine News from Burgundy 1961",
  "publisher": "Sherry Wine & Spirits Co.,Inc.",
  "publication_date": 1961
}
{
  "page_ark": "d7k30d-001",
  "ark": "d7k30d",
  "page": 1,
  "name": "BEAUNE GREVES",
  "year_published": 1961,
  "vintage": null,
  "type": "wine",
  "color": null,
  "country": "France",
  "section": null,
  "bottle_type": null,
  "perprice": 3.29,
  "caseprice": 36.25,
  "bbox": "{\"type\":\"Polygon\",\"coordinates\":[[[1983.5,-1564],[1983.5,-1532],[3596,-1532],[3596,-1564],[1983.5,-1564]]]}",
  "title": "Exciting Wine News from Burgundy 1961",
  "publisher": "Sherry Wine & Spirits Co.,Inc.",
  "publication_date": 1961
}
{
  "page_ark": "d7k30d-002",
  "ark": "d7k30d",
  "page": 2,
  "name": "TOUR CARNET (Medoc) WSK",
  "year_published": 1961,
  "vintage": null,
  "type": "wine",
  "color": null,
  "country": "France",
  "section": null,
  "bottle_type": null,
  "perprice": 22.65,
  "caseprice": null,
  "bbox": "{\"type\":\"Polygon\",\"coordinates\":[[[239,-3416],[239,-3377],[1864,-3377],[1864,-3416],[239,-3416]]]}",
  "title": "Exciting Wine News from Burgundy 1961",
  "publisher": "Sherry Wine & Spirits Co.,Inc.",
  "publication_date": 1961
}
{
  "page_ark": "d7k30d-002",
  "ark": "d7k30d",
  "page": 2,
  "name": "CHATEAU RIPEAU (Saint",
  "year_published": 1961,
  "vintage": null,
  "type": "wine",
  "color": null,
  "country": "France",
  "section": null,
  "bottle_type": null,
  "perprice": 25,
  "caseprice": null,
  "bbox": "{\"type\":\"Polygon\",\"coordinates\":[[[239,-3667],[239,-3629],[1866,-3629],[1866,-3667],[239,-3667]]]}",
  "title": "Exciting Wine News from Burgundy 1961",
  "publisher": "Sherry Wine & Spirits Co.,Inc.",
  "publication_date": 1961
}
{
  "page_ark": "d7k30d-002",
  "ark": "d7k30d",
  "page": 2,
  "name": "CHATEAU HAUT BRION (Graves)",
  "year_published": 1961,
  "vintage": null,
  "type": "wine",
  "color": null,
  "country": "France",
  "section": null,
  "bottle_type": null,
  "perprice": 87.5,
  "caseprice": null,
  "bbox": "{\"type\":\"Polygon\",\"coordinates\":[[[1968,-4858],[1968,-4820],[3610,-4820],[3610,-4858],[1968,-4858]]]}",
  "title": "Exciting Wine News from Burgundy 1961",
  "publisher": "Sherry Wine & Spirits Co.,Inc.",
  "publication_date": 1961
}
{
  "page_ark": "d7k30d-003",
  "ark": "d7k30d",
  "page": 3,
  "name": "Volnay unmistakable",
  "year_published": 1961,
  "vintage": 1959,
  "type": "wine",
  "color": null,
  "country": "France",
  "section": null,
  "bottle_type": null,
  "perprice": 19.59,
  "caseprice": null,
  "bbox": "{\"type\":\"Polygon\",\"coordinates\":[[[341.666666666667,-2759],[341.666666666667,-2726],[1729,-2726],[1729,-2759],[341.666666666667,-2759]]]}",
  "title": "Exciting Wine News from Burgundy 1961",
  "publisher": "Sherry Wine & Spirits Co.,Inc.",
  "publication_date": 1961
}
{
  "page_ark": "d7k30d-003",
  "ark": "d7k30d",
  "page": 3,
  "name": "POUILLY VINZELLES",
  "year_published": 1961,
  "vintage": 1959,
  "type": "wine",
  "color": null,
  "country": "France",
  "section": null,
  "bottle_type": null,
  "perprice": 1.89,
  "caseprice": null,
  "bbox": "{\"type\":\"Polygon\",\"coordinates\":[[[230.5,-4320],[230.5,-4282],[1861,-4282],[1861,-4320],[230.5,-4320]]]}",
  "title": "Exciting Wine News from Burgundy 1961",
  "publisher": "Sherry Wine & Spirits Co.,Inc.",
  "publication_date": 1961
}
{
  "page_ark": "d7k30d-003",
  "ark": "d7k30d",
  "page": 3,
  "name": "BONNES MARES",
  "year_published": 1961,
  "vintage": null,
  "type": "wine",
  "color": null,
  "country": "France",
  "section": null,
  "bottle_type": null,
  "perprice": 52.75,
  "caseprice": null,
  "bbox": "{\"type\":\"Polygon\",\"coordinates\":[[[341.666666666667,-1448],[341.666666666667,-1406],[1843,-1406],[1843,-1448],[341.666666666667,-1448]]]}",
  "title": "Exciting Wine News from Burgundy 1961",
  "publisher": "Sherry Wine & Spirits Co.,Inc.",
  "publication_date": 1961
}
{
  "page_ark": "d7k30d-001",
  "ark": "d7k30d",
  "page": 1,
  "name": "VOLNAY CHAMPANS",
  "year_published": 1961,
  "vintage": null,
  "type": "wine",
  "color": null,
  "country": "France",
  "section": null,
  "bottle_type": null,
  "perprice": 3.29,
  "caseprice": 36.75,
  "bbox": "{\"type\":\"Polygon\",\"coordinates\":[[[1987.5,-1914],[1987.5,-1881],[3623,-1881],[3623,-1914],[1987.5,-1914]]]}",
  "title": "Exciting Wine News from Burgundy 1961",
  "publisher": "Sherry Wine & Spirits Co.,Inc.",
  "publication_date": 1961
}
{
  "page_ark": "d7k30d-002",
  "ark": "d7k30d",
  "page": 2,
  "name": "CHATEAU ROC (Cotes de Bourg)",
  "year_published": 1961,
  "vintage": null,
  "type": "wine",
  "color": null,
  "country": "France",
  "section": null,
  "bottle_type": null,
  "perprice": 16,
  "caseprice": null,
  "bbox": "{\"type\":\"Polygon\",\"coordinates\":[[[239,-3255],[239,-3216],[1867,-3216],[1867,-3255],[239,-3255]]]}",
  "title": "Exciting Wine News from Burgundy 1961",
  "publisher": "Sherry Wine & Spirits Co.,Inc.",
  "publication_date": 1961
}
{
  "page_ark": "d7k30d-002",
  "ark": "d7k30d",
  "page": 2,
  "name": "CHATEAU TALBOT (Saint Julien)",
  "year_published": 1961,
  "vintage": null,
  "type": "wine",
  "color": null,
  "country": "France",
  "section": null,
  "bottle_type": null,
  "perprice": 40,
  "caseprice": null,
  "bbox": "{\"type\":\"Polygon\",\"coordinates\":[[[1961,-2258],[1961,-2224],[3603,-2224],[3603,-2258],[1961,-2258]]]}",
  "title": "Exciting Wine News from Burgundy 1961",
  "publisher": "Sherry Wine & Spirits Co.,Inc.",
  "publication_date": 1961
}
{
  "page_ark": "d7k30d-003",
  "ark": "d7k30d",
  "page": 3,
  "name": "BEAUNE GUIGONE DE SALINS",
  "year_published": 1961,
  "vintage": null,
  "type": "wine",
  "color": null,
  "country": "France",
  "section": null,
  "bottle_type": null,
  "perprice": 5.99,
  "caseprice": null,
  "bbox": "{\"type\":\"Polygon\",\"coordinates\":[[[226.5,-3708],[226.5,-3672],[1549,-3672],[1549,-3708],[226.5,-3708]]]}",
  "title": "Exciting Wine News from Burgundy 1961",
  "publisher": "Sherry Wine & Spirits Co.,Inc.",
  "publication_date": 1961
}
{
  "page_ark": "d7k30d-002",
  "ark": "d7k30d",
  "page": 2,
  "name": "The listed",
  "year_published": 1961,
  "vintage": null,
  "type": "wine",
  "color": null,
  "country": null,
  "section": null,
  "bottle_type": null,
  "perprice": 19.59,
  "caseprice": null,
  "bbox": "{\"type\":\"Polygon\",\"coordinates\":[[[239,-2312],[239,-2273],[1860,-2273],[1860,-2312],[239,-2312]]]}",
  "title": "Exciting Wine News from Burgundy 1961",
  "publisher": "Sherry Wine & Spirits Co.,Inc.",
  "publication_date": 1961
}
{
  "page_ark": "d7k30d-002",
  "ark": "d7k30d",
  "page": 2,
  "name": "NENIN (Pomerol)",
  "year_published": 1961,
  "vintage": null,
  "type": "wine",
  "color": null,
  "country": "France",
  "section": null,
  "bottle_type": null,
  "perprice": 32.5,
  "caseprice": null,
  "bbox": "{\"type\":\"Polygon\",\"coordinates\":[[[248,-4832],[248,-4801],[1877,-4801],[1877,-4832],[248,-4832]]]}",
  "title": "Exciting Wine News from Burgundy 1961",
  "publisher": "Sherry Wine & Spirits Co.,Inc.",
  "publication_date": 1961
}
{
  "page_ark": "d7k30d-002",
  "ark": "d7k30d",
  "page": 2,
  "name": "Wine consistently CHATEAU MARGAUX",
  "year_published": 1961,
  "vintage": 1955,
  "type": "wine",
  "color": null,
  "country": "France",
  "section": null,
  "bottle_type": null,
  "perprice": 85,
  "caseprice": null,
  "bbox": "{\"type\":\"Polygon\",\"coordinates\":[[[1961,-4090],[1961,-4056],[3615,-4056],[3615,-4090],[1961,-4090]]]}",
  "title": "Exciting Wine News from Burgundy 1961",
  "publisher": "Sherry Wine & Spirits Co.,Inc.",
  "publication_date": 1961
}
{
  "page_ark": "d7k30d-001",
  "ark": "d7k30d",
  "page": 1,
  "name": "CHAMBOLLE MUSIGNY",
  "year_published": 1961,
  "vintage": null,
  "type": "wine",
  "color": null,
  "country": "France",
  "section": null,
  "bottle_type": null,
  "perprice": 2.79,
  "caseprice": 30.75,
  "bbox": "{\"type\":\"Polygon\",\"coordinates\":[[[223.666666666667,-4682],[223.666666666667,-4638],[1858,-4638],[1858,-4682],[223.666666666667,-4682]]]}",
  "title": "Exciting Wine News from Burgundy 1961",
  "publisher": "Sherry Wine & Spirits Co.,Inc.",
  "publication_date": 1961
}
{
  "page_ark": "d7k30d-001",
  "ark": "d7k30d",
  "page": 1,
  "name": "Musigny Grands Echezeaux This best Clos",
  "year_published": 1961,
  "vintage": null,
  "type": "wine",
  "color": null,
  "country": "France",
  "section": null,
  "bottle_type": null,
  "perprice": 19.59,
  "caseprice": null,
  "bbox": "{\"type\":\"Polygon\",\"coordinates\":[[[1986.7,-5051],[1986.7,-5017],[3266,-5017],[3266,-5051],[1986.7,-5051]]]}",
  "title": "Exciting Wine News from Burgundy 1961",
  "publisher": "Sherry Wine & Spirits Co.,Inc.",
  "publication_date": 1961
}
{
  "page_ark": "d7k30d-001",
  "ark": "d7k30d",
  "page": 1,
  "name": "POMMARD RUGIENS",
  "year_published": 1961,
  "vintage": null,
  "type": "wine",
  "color": null,
  "country": "France",
  "section": null,
  "bottle_type": null,
  "perprice": 19.59,
  "caseprice": null,
  "bbox": "{\"type\":\"Polygon\",\"coordinates\":[[[1989.5,-3286],[1989.5,-2065],[3625,-2065],[3625,-3286],[1989.5,-3286]]]}",
  "title": "Exciting Wine News from Burgundy 1961",
  "publisher": "Sherry Wine & Spirits Co.,Inc.",
  "publication_date": 1961
}
{
  "page_ark": "d7k30d-002",
  "ark": "d7k30d",
  "page": 2,
  "name": "CHATEAU BEYCHEVELLE (Saint Julien)",
  "year_published": 1961,
  "vintage": null,
  "type": "wine",
  "color": null,
  "country": "France",
  "section": null,
  "bottle_type": null,
  "perprice": 45,
  "caseprice": null,
  "bbox": "{\"type\":\"Polygon\",\"coordinates\":[[[1961,-3554],[1961,-3511],[3612,-3511],[3612,-3554],[1961,-3554]]]}",
  "title": "Exciting Wine News from Burgundy 1961",
  "publisher": "Sherry Wine & Spirits Co.,Inc.",
  "publication_date": 1961
}
{
  "page_ark": "d7k30d-002",
  "ark": "d7k30d",
  "page": 2,
  "name": "CHATEAU CALON SEGUR (Saint Estephe)",
  "year_published": 1961,
  "vintage": null,
  "type": "wine",
  "color": null,
  "country": "France",
  "section": null,
  "bottle_type": null,
  "perprice": 45,
  "caseprice": null,
  "bbox": "{\"type\":\"Polygon\",\"coordinates\":[[[1960,-3680],[1960,-3637],[3614,-3637],[3614,-3680],[1960,-3680]]]}",
  "title": "Exciting Wine News from Burgundy 1961",
  "publisher": "Sherry Wine & Spirits Co.,Inc.",
  "publication_date": 1961
}
{
  "page_ark": "d7k30d-002",
  "ark": "d7k30d",
  "page": 2,
  "name": "Fantastic Mouton Rothschil CHATEAU MALESCOT (Margaux)",
  "year_published": 1961,
  "vintage": null,
  "type": "wine",
  "color": null,
  "country": "France",
  "section": null,
  "bottle_type": null,
  "perprice": 39.5,
  "caseprice": null,
  "bbox": "{\"type\":\"Polygon\",\"coordinates\":[[[1961,-1913],[1961,-1871],[3602,-1871],[3602,-1913],[1961,-1913]]]}",
  "title": "Exciting Wine News from Burgundy 1961",
  "publisher": "Sherry Wine & Spirits Co.,Inc.",
  "publication_date": 1961
}
{
  "page_ark": "d7k30d-003",
  "ark": "d7k30d",
  "page": 3,
  "name": "CHARMES CHAMBERTIN",
  "year_published": 1961,
  "vintage": null,
  "type": "wine",
  "color": null,
  "country": "France",
  "section": null,
  "bottle_type": null,
  "perprice": 55,
  "caseprice": null,
  "bbox": "{\"type\":\"Polygon\",\"coordinates\":[[[341.666666666667,-1778],[341.666666666667,-1734],[1845,-1734],[1845,-1778],[341.666666666667,-1778]]]}",
  "title": "Exciting Wine News from Burgundy 1961",
  "publisher": "Sherry Wine & Spirits Co.,Inc.",
  "publication_date": 1961
}
{
  "page_ark": "d7k30d-003",
  "ark": "d7k30d",
  "page": 3,
  "name": "POMMARD",
  "year_published": 1961,
  "vintage": null,
  "type": "wine",
  "color": "white",
  "country": "France",
  "section": null,
  "bottle_type": null,
  "perprice": 5.99,
  "caseprice": 43.05,
  "bbox": "{\"type\":\"Polygon\",\"coordinates\":[[[1953.1,-3350],[1953.1,-3309],[3578,-3309],[3578,-3350],[1953.1,-3350]]]}",
  "title": "Exciting Wine News from Burgundy 1961",
  "publisher": "Sherry Wine & Spirits Co.,Inc.",
  "publication_date": 1961
}
{
  "page_ark": "d7k30d-001",
  "ark": "d7k30d",
  "page": 1,
  "name": "FLEURIE LES MORIERS",
  "year_published": 1961,
  "vintage": null,
  "type": "wine",
  "color": null,
  "country": null,
  "section": null,
  "bottle_type": null,
  "perprice": 2.19,
  "caseprice": 24.5,
  "bbox": "{\"type\":\"Polygon\",\"coordinates\":[[[223.666666666667,-4066],[223.666666666667,-4022],[1866,-4022],[1866,-4066],[223.666666666667,-4066]]]}",
  "title": "Exciting Wine News from Burgundy 1961",
  "publisher": "Sherry Wine & Spirits Co.,Inc.",
  "publication_date": 1961
}
{
  "page_ark": "d7k30d-001",
  "ark": "d7k30d",
  "page": 1,
  "name": "GEVRY CHAMBERTIN SAINT JACQUE",
  "year_published": 1961,
  "vintage": null,
  "type": "wine",
  "color": null,
  "country": "France",
  "section": null,
  "bottle_type": null,
  "perprice": 3.49,
  "caseprice": 38.5,
  "bbox": "{\"type\":\"Polygon\",\"coordinates\":[[[1989.5,-3975],[1989.5,-2254],[3609,-2254],[3609,-3975],[1989.5,-3975]]]}",
  "title": "Exciting Wine News from Burgundy 1961",
  "publisher": "Sherry Wine & Spirits Co.,Inc.",
  "publication_date": 1961
}
{
  "page_ark": "d7k30d-003",
  "ark": "d7k30d",
  "page": 3,
  "name": "BEAUJOLAIS BLANC",
  "year_published": 1961,
  "vintage": 1959,
  "type": "wine",
  "color": "white",
  "country": "France",
  "section": null,
  "bottle_type": null,
  "perprice": 22.65,
  "caseprice": null,
  "bbox": "{\"type\":\"Polygon\",\"coordinates\":[[[341.666666666667,-4687],[341.666666666667,-4636],[1869,-4636],[1869,-4687],[341.666666666667,-4687]]]}",
  "title": "Exciting Wine News from Burgundy 1961",
  "publisher": "Sherry Wine & Spirits Co.,Inc.",
  "publication_date": 1961
}
{
  "page_ark": "d7k30d-001",
  "ark": "d7k30d",
  "page": 1,
  "name": "VOSNE ROMANEE CLOS DES REAS",
  "year_published": 1961,
  "vintage": null,
  "type": "wine",
  "color": null,
  "country": "France",
  "section": null,
  "bottle_type": null,
  "perprice": 3.99,
  "caseprice": 43.95,
  "bbox": "{\"type\":\"Polygon\",\"coordinates\":[[[1986.7,-3665],[1986.7,-3622],[3603,-3622],[3603,-3665],[1986.7,-3665]]]}",
  "title": "Exciting Wine News from Burgundy 1961",
  "publisher": "Sherry Wine & Spirits Co.,Inc.",
  "publication_date": 1961
}
{
  "page_ark": "d7k30d-002",
  "ark": "d7k30d",
  "page": 2,
  "name": "CHATEAU PICHON LONGUEVILLE BAROM (Pauillac)",
  "year_published": 1961,
  "vintage": null,
  "type": "wine",
  "color": null,
  "country": "France",
  "section": null,
  "bottle_type": null,
  "perprice": 37.5,
  "caseprice": null,
  "bbox": "{\"type\":\"Polygon\",\"coordinates\":[[[1964,-1533],[1964,-1491],[3602,-1491],[3602,-1533],[1964,-1533]]]}",
  "title": "Exciting Wine News from Burgundy 1961",
  "publisher": "Sherry Wine & Spirits Co.,Inc.",
  "publication_date": 1961
}
{
  "page_ark": "d7k30d-002",
  "ark": "d7k30d",
  "page": 2,
  "name": "SPLICE Matisse CHATEAU LATOUR (Pauillac)",
  "year_published": 1961,
  "vintage": null,
  "type": "wine",
  "color": null,
  "country": "France",
  "section": null,
  "bottle_type": null,
  "perprice": 85,
  "caseprice": null,
  "bbox": "{\"type\":\"Polygon\",\"coordinates\":[[[1961,-3975],[1961,-3933],[3617,-3933],[3617,-3975],[1961,-3975]]]}",
  "title": "Exciting Wine News from Burgundy 1961",
  "publisher": "Sherry Wine & Spirits Co.,Inc.",
  "publication_date": 1961
}
{
  "page_ark": "d7k30d-003",
  "ark": "d7k30d",
  "page": 3,
  "name": "POUILLY VINZELLES",
  "year_published": 1961,
  "vintage": 1959,
  "type": "wine",
  "color": null,
  "country": "France",
  "section": null,
  "bottle_type": null,
  "perprice": 21.5,
  "caseprice": null,
  "bbox": "{\"type\":\"Polygon\",\"coordinates\":[[[341.666666666667,-4323],[341.666666666667,-4271],[1867,-4271],[1867,-4323],[341.666666666667,-4323]]]}",
  "title": "Exciting Wine News from Burgundy 1961",
  "publisher": "Sherry Wine & Spirits Co.,Inc.",
  "publication_date": 1961
}
{
  "page_ark": "d7k30d-003",
  "ark": "d7k30d",
  "page": 3,
  "name": "MONTRACHET PULIGNY 699",
  "year_published": 1961,
  "vintage": null,
  "type": "wine",
  "color": null,
  "country": "France",
  "section": null,
  "bottle_type": null,
  "perprice": 2.49,
  "caseprice": 27.5,
  "bbox": "{\"type\":\"Polygon\",\"coordinates\":[[[1953.1,-1305],[1953.1,-1268],[3580,-1268],[3580,-1305],[1953.1,-1305]]]}",
  "title": "Exciting Wine News from Burgundy 1961",
  "publisher": "Sherry Wine & Spirits Co.,Inc.",
  "publication_date": 1961
}
{
  "page_ark": "d7k30d-003",
  "ark": "d7k30d",
  "page": 3,
  "name": "",
  "year_published": 1961,
  "vintage": null,
  "type": "wine",
  "color": null,
  "country": null,
  "section": null,
  "bottle_type": null,
  "perprice": 2.99,
  "caseprice": 32.95,
  "bbox": "{\"type\":\"Polygon\",\"coordinates\":[[[1953.1,-1707],[1953.1,-1672],[3572,-1672],[3572,-1707],[1953.1,-1707]]]}",
  "title": "Exciting Wine News from Burgundy 1961",
  "publisher": "Sherry Wine & Spirits Co.,Inc.",
  "publication_date": 1961
}
{
  "page_ark": "d7k30d-003",
  "ark": "d7k30d",
  "page": 3,
  "name": "MEURSAULT CHARMES",
  "year_published": 1961,
  "vintage": null,
  "type": "wine",
  "color": null,
  "country": "France",
  "section": null,
  "bottle_type": null,
  "perprice": 3.99,
  "caseprice": 43.95,
  "bbox": "{\"type\":\"Polygon\",\"coordinates\":[[[1961.5,-2032],[1961.5,-1994],[3575,-1994],[3575,-2032],[1961.5,-2032]]]}",
  "title": "Exciting Wine News from Burgundy 1961",
  "publisher": "Sherry Wine & Spirits Co.,Inc.",
  "publication_date": 1961
}
{
  "page_ark": "d7k30d-001",
  "ark": "d7k30d",
  "page": 1,
  "name": "France Simultaneously 1mp The",
  "year_published": 1961,
  "vintage": null,
  "type": "wine",
  "color": null,
  "country": null,
  "section": null,
  "bottle_type": null,
  "perprice": 19.59,
  "caseprice": null,
  "bbox": "{\"type\":\"Polygon\",\"coordinates\":[[[223.666666666667,-2180],[223.666666666667,-2138],[1546,-2138],[1546,-2180],[223.666666666667,-2180]]]}",
  "title": "Exciting Wine News from Burgundy 1961",
  "publisher": "Sherry Wine & Spirits Co.,Inc.",
  "publication_date": 1961
}
{
  "page_ark": "d7k30d-002",
  "ark": "d7k30d",
  "page": 2,
  "name": "CHATEAU KIRWAN (Haut Medoc)",
  "year_published": 1961,
  "vintage": null,
  "type": "wine",
  "color": null,
  "country": "France",
  "section": null,
  "bottle_type": null,
  "perprice": 29.75,
  "caseprice": null,
  "bbox": "{\"type\":\"Polygon\",\"coordinates\":[[[241,-4263],[241,-4230],[1868,-4230],[1868,-4263],[241,-4263]]]}",
  "title": "Exciting Wine News from Burgundy 1961",
  "publisher": "Sherry Wine & Spirits Co.,Inc.",
  "publication_date": 1961
}
{
  "page_ark": "d7k30d-002",
  "ark": "d7k30d",
  "page": 2,
  "name": "Maintains All CHATEAU CANON (Saint Emilion)",
  "year_published": 1961,
  "vintage": null,
  "type": "wine",
  "color": null,
  "country": "France",
  "section": null,
  "bottle_type": null,
  "perprice": 32,
  "caseprice": null,
  "bbox": "{\"type\":\"Polygon\",\"coordinates\":[[[239,-4672],[239,-4631],[1874,-4631],[1874,-4672],[239,-4672]]]}",
  "title": "Exciting Wine News from Burgundy 1961",
  "publisher": "Sherry Wine & Spirits Co.,Inc.",
  "publication_date": 1961
}
{
  "page_ark": "d7k30d-002",
  "ark": "d7k30d",
  "page": 2,
  "name": "CHATEAU (Saint Emilion)",
  "year_published": 1961,
  "vintage": null,
  "type": "wine",
  "color": null,
  "country": "France",
  "section": null,
  "bottle_type": null,
  "perprice": 29,
  "caseprice": null,
  "bbox": "{\"type\":\"Polygon\",\"coordinates\":[[[241,-3747],[241,-3709],[1864,-3709],[1864,-3747],[241,-3747]]]}",
  "title": "Exciting Wine News from Burgundy 1961",
  "publisher": "Sherry Wine & Spirits Co.,Inc.",
  "publication_date": 1961
}
{
  "page_ark": "d7k30d-002",
  "ark": "d7k30d",
  "page": 2,
  "name": "Typical Pauillac rounded deep 709 CHATEAU VIEUX CERTAN (Pomerol)",
  "year_published": 1961,
  "vintage": null,
  "type": "wine",
  "color": null,
  "country": "France",
  "section": null,
  "bottle_type": null,
  "perprice": 37.5,
  "caseprice": null,
  "bbox": "{\"type\":\"Polygon\",\"coordinates\":[[[1961,-1660],[1961,-1618],[3602,-1618],[3602,-1660],[1961,-1660]]]}",
  "title": "Exciting Wine News from Burgundy 1961",
  "publisher": "Sherry Wine & Spirits Co.,Inc.",
  "publication_date": 1961
}
{
  "page_ark": "d7k30d-003",
  "ark": "d7k30d",
  "page": 3,
  "name": "GRANDS ECHEZEAUX",
  "year_published": 1961,
  "vintage": null,
  "type": "wine",
  "color": null,
  "country": "France",
  "section": null,
  "bottle_type": null,
  "perprice": 55,
  "caseprice": null,
  "bbox": "{\"type\":\"Polygon\",\"coordinates\":[[[341.666666666667,-2382],[341.666666666667,-2339],[1844,-2339],[1844,-2382],[341.666666666667,-2382]]]}",
  "title": "Exciting Wine News from Burgundy 1961",
  "publisher": "Sherry Wine & Spirits Co.,Inc.",
  "publication_date": 1961
}
{
  "page_ark": "d7k30d-003",
  "ark": "d7k30d",
  "page": 3,
  "name": "CHAMBERTIN CLOS DE BEZE",
  "year_published": 1961,
  "vintage": null,
  "type": "wine",
  "color": null,
  "country": "France",
  "section": null,
  "bottle_type": null,
  "perprice": 66,
  "caseprice": null,
  "bbox": "{\"type\":\"Polygon\",\"coordinates\":[[[341.666666666667,-3039],[341.666666666667,-2996],[1848,-2996],[1848,-3039],[341.666666666667,-3039]]]}",
  "title": "Exciting Wine News from Burgundy 1961",
  "publisher": "Sherry Wine & Spirits Co.,Inc.",
  "publication_date": 1961
}
{
  "page_ark": "d7k30d-003",
  "ark": "d7k30d",
  "page": 3,
  "name": "BEAUNE GUIGONE DE SALINS",
  "year_published": 1961,
  "vintage": null,
  "type": "wine",
  "color": null,
  "country": "France",
  "section": null,
  "bottle_type": null,
  "perprice": 66,
  "caseprice": null,
  "bbox": "{\"type\":\"Polygon\",\"coordinates\":[[[341.666666666667,-3708],[341.666666666667,-3660],[1857,-3660],[1857,-3708],[341.666666666667,-3708]]]}",
  "title": "Exciting Wine News from Burgundy 1961",
  "publisher": "Sherry Wine & Spirits Co.,Inc.",
  "publication_date": 1961
}
{
  "page_ark": "d7k30d-003",
  "ark": "d7k30d",
  "page": 3,
  "name": "CORTON CHARLEMAGNE Eada",
  "year_published": 1961,
  "vintage": null,
  "type": "wine",
  "color": null,
  "country": "France",
  "section": null,
  "bottle_type": null,
  "perprice": 4.19,
  "caseprice": 46.25,
  "bbox": "{\"type\":\"Polygon\",\"coordinates\":[[[1959.5,-3768],[1959.5,-3730],[3576,-3730],[3576,-3768],[1959.5,-3768]]]}",
  "title": "Exciting Wine News from Burgundy 1961",
  "publisher": "Sherry Wine & Spirits Co.,Inc.",
  "publication_date": 1961
}
{
  "page_ark": "d7k30d-001",
  "ark": "d7k30d",
  "page": 1,
  "name": "MOULIN VENT BURDELINES",
  "year_published": 1961,
  "vintage": null,
  "type": "wine",
  "color": null,
  "country": null,
  "section": null,
  "bottle_type": null,
  "perprice": 2.19,
  "caseprice": 24.5,
  "bbox": "{\"type\":\"Polygon\",\"coordinates\":[[[223.666666666667,-3714],[223.666666666667,-3672],[1868,-3672],[1868,-3714],[223.666666666667,-3714]]]}",
  "title": "Exciting Wine News from Burgundy 1961",
  "publisher": "Sherry Wine & Spirits Co.,Inc.",
  "publication_date": 1961
}
{
  "page_ark": "d7k30d-001",
  "ark": "d7k30d",
  "page": 1,
  "name": "CHASSAGNE MONTRACHET CAILLERETS",
  "year_published": 1961,
  "vintage": null,
  "type": "wine",
  "color": null,
  "country": "France",
  "section": null,
  "bottle_type": null,
  "perprice": 32.95,
  "caseprice": null,
  "bbox": "{\"type\":\"Polygon\",\"coordinates\":[[[1989.5,-1267],[1989.5,-1223],[3599,-1223],[3599,-1267],[1989.5,-1267]]]}",
  "title": "Exciting Wine News from Burgundy 1961",
  "publisher": "Sherry Wine & Spirits Co.,Inc.",
  "publication_date": 1961
}
{
  "page_ark": "d7k30d-001",
  "ark": "d7k30d",
  "page": 1,
  "name": "JACQUES SAINT GEVRY CHAMBERTIN 226",
  "year_published": 1961,
  "vintage": null,
  "type": "wine",
  "color": null,
  "country": "France",
  "section": null,
  "bottle_type": null,
  "perprice": 3.99,
  "caseprice": 43.95,
  "bbox": "{\"type\":\"Polygon\",\"coordinates\":[[[1986.7,-4016],[1986.7,-3964],[3630,-3964],[3630,-4016],[1986.7,-4016]]]}",
  "title": "Exciting Wine News from Burgundy 1961",
  "publisher": "Sherry Wine & Spirits Co.,Inc.",
  "publication_date": 1961
}
{
  "page_ark": "d7k30d-002",
  "ark": "d7k30d",
  "page": 2,
  "name": "CHATEAU BATAILLEY (Haut Medoc)",
  "year_published": 1961,
  "vintage": null,
  "type": "wine",
  "color": null,
  "country": "France",
  "section": null,
  "bottle_type": null,
  "perprice": 34.5,
  "caseprice": null,
  "bbox": "{\"type\":\"Polygon\",\"coordinates\":[[[239,-3904],[239,-3869],[1865,-3869],[1865,-3904],[239,-3904]]]}",
  "title": "Exciting Wine News from Burgundy 1961",
  "publisher": "Sherry Wine & Spirits Co.,Inc.",
  "publication_date": 1961
}
{
  "page_ark": "d7k30d-003",
  "ark": "d7k30d",
  "page": 3,
  "name": "CORTON",
  "year_published": 1961,
  "vintage": null,
  "type": "wine",
  "color": null,
  "country": "France",
  "section": null,
  "bottle_type": null,
  "perprice": 55,
  "caseprice": null,
  "bbox": "{\"type\":\"Polygon\",\"coordinates\":[[[341.666666666667,-2055],[341.666666666667,-2012],[1845,-2012],[1845,-2055],[341.666666666667,-2055]]]}",
  "title": "Exciting Wine News from Burgundy 1961",
  "publisher": "Sherry Wine & Spirits Co.,Inc.",
  "publication_date": 1961
}
{
  "page_ark": "d7k30d-003",
  "ark": "d7k30d",
  "page": 3,
  "name": "VOLNAY CUVEE BLONDEAU",
  "year_published": 1961,
  "vintage": null,
  "type": "wine",
  "color": null,
  "country": "France",
  "section": null,
  "bottle_type": null,
  "perprice": 59.95,
  "caseprice": null,
  "bbox": "{\"type\":\"Polygon\",\"coordinates\":[[[341.666666666667,-2659],[341.666666666667,-2616],[1843,-2616],[1843,-2659],[341.666666666667,-2659]]]}",
  "title": "Exciting Wine News from Burgundy 1961",
  "publisher": "Sherry Wine & Spirits Co.,Inc.",
  "publication_date": 1961
}
{
  "page_ark": "d7k30d-003",
  "ark": "d7k30d",
  "page": 3,
  "name": "CLOS BLANC DE VOUGEOT",
  "year_published": 1961,
  "vintage": null,
  "type": "wine",
  "color": "white",
  "country": "France",
  "section": null,
  "bottle_type": null,
  "perprice": 4.49,
  "caseprice": 49.75,
  "bbox": "{\"type\":\"Polygon\",\"coordinates\":[[[1953.5,-4102],[1953.5,-4064],[3572,-4064],[3572,-4102],[1953.5,-4102]]]}",
  "title": "Exciting Wine News from Burgundy 1961",
  "publisher": "Sherry Wine & Spirits Co.,Inc.",
  "publication_date": 1961
}
{
  "page_ark": "d7k30d-003",
  "ark": "d7k30d",
  "page": 3,
  "name": "CHAMBERTIN CLOS DE BEZE",
  "year_published": 1961,
  "vintage": null,
  "type": "wine",
  "color": null,
  "country": "France",
  "section": null,
  "bottle_type": null,
  "perprice": 5.99,
  "caseprice": null,
  "bbox": "{\"type\":\"Polygon\",\"coordinates\":[[[235.5,-3039],[235.5,-2999],[1552,-2999],[1552,-3039],[235.5,-3039]]]}",
  "title": "Exciting Wine News from Burgundy 1961",
  "publisher": "Sherry Wine & Spirits Co.,Inc.",
  "publication_date": 1961
}
{
  "page_ark": "d7k30d-001",
  "ark": "d7k30d",
  "page": 1,
  "name": "POMMARD LES EPENOTS",
  "year_published": 1961,
  "vintage": null,
  "type": "wine",
  "color": null,
  "country": "France",
  "section": null,
  "bottle_type": null,
  "perprice": 3.99,
  "caseprice": 43.98,
  "bbox": "{\"type\":\"Polygon\",\"coordinates\":[[[1986.7,-2965],[1986.7,-2929],[3607,-2929],[3607,-2965],[1986.7,-2965]]]}",
  "title": "Exciting Wine News from Burgundy 1961",
  "publisher": "Sherry Wine & Spirits Co.,Inc.",
  "publication_date": 1961
}
{
  "page_ark": "d7k30d-002",
  "ark": "d7k30d",
  "page": 2,
  "name": "CHATEAU GISCOURS (Margaux)",
  "year_published": 1961,
  "vintage": null,
  "type": "wine",
  "color": null,
  "country": "France",
  "section": null,
  "bottle_type": null,
  "perprice": 34.5,
  "caseprice": null,
  "bbox": "{\"type\":\"Polygon\",\"coordinates\":[[[239,-4991],[239,-4962],[1878,-4962],[1878,-4991],[239,-4991]]]}",
  "title": "Exciting Wine News from Burgundy 1961",
  "publisher": "Sherry Wine & Spirits Co.,Inc.",
  "publication_date": 1961
}
{
  "page_ark": "d7k30d-002",
  "ark": "d7k30d",
  "page": 2,
  "name": "CHATEAU GRACE DIEU (Saint Emilion)",
  "year_published": 1961,
  "vintage": null,
  "type": "wine",
  "color": null,
  "country": "France",
  "section": null,
  "bottle_type": null,
  "perprice": 24.75,
  "caseprice": null,
  "bbox": "{\"type\":\"Polygon\",\"coordinates\":[[[239,-3587],[239,-3549],[1863,-3549],[1863,-3587],[239,-3587]]]}",
  "title": "Exciting Wine News from Burgundy 1961",
  "publisher": "Sherry Wine & Spirits Co.,Inc.",
  "publication_date": 1961
}
{
  "page_ark": "d7k30d-002",
  "ark": "d7k30d",
  "page": 2,
  "name": "PRIEURE LICHINE (Margaux)",
  "year_published": 1961,
  "vintage": null,
  "type": "wine",
  "color": null,
  "country": "France",
  "section": null,
  "bottle_type": null,
  "perprice": 29.5,
  "caseprice": null,
  "bbox": "{\"type\":\"Polygon\",\"coordinates\":[[[240,-3827],[240,-3790],[1863,-3790],[1863,-3827],[240,-3827]]]}",
  "title": "Exciting Wine News from Burgundy 1961",
  "publisher": "Sherry Wine & Spirits Co.,Inc.",
  "publication_date": 1961
}
{
  "page_ark": "d7k30d-002",
  "ark": "d7k30d",
  "page": 2,
  "name": "CHATEAU GRUAUD LAROSE (Saint Julien)",
  "year_published": 1961,
  "vintage": null,
  "type": "wine",
  "color": "rose",
  "country": "France",
  "section": null,
  "bottle_type": null,
  "perprice": 42.5,
  "caseprice": null,
  "bbox": "{\"type\":\"Polygon\",\"coordinates\":[[[1962,-3169],[1962,-3131],[3607,-3131],[3607,-3169],[1962,-3169]]]}",
  "title": "Exciting Wine News from Burgundy 1961",
  "publisher": "Sherry Wine & Spirits Co.,Inc.",
  "publication_date": 1961
}
{
  "page_ark": "d7k30d-002",
  "ark": "d7k30d",
  "page": 2,
  "name": "CHATEAU AUSONE (Saint Emilion)",
  "year_published": 1961,
  "vintage": null,
  "type": "wine",
  "color": null,
  "country": "France",
  "section": null,
  "bottle_type": null,
  "perprice": 87.5,
  "caseprice": null,
  "bbox": "{\"type\":\"Polygon\",\"coordinates\":[[[1961,-4437],[1961,-4396],[3611,-4396],[3611,-4437],[1961,-4437]]]}",
  "title": "Exciting Wine News from Burgundy 1961",
  "publisher": "Sherry Wine & Spirits Co.,Inc.",
  "publication_date": 1961
}
{
  "page_ark": "d7k30d-002",
  "ark": "d7k30d",
  "page": 2,
  "name": "CHATEAU LEOVILLE LASCASES (Saint Julien)",
  "year_published": 1961,
  "vintage": null,
  "type": "wine",
  "color": null,
  "country": "US",
  "section": null,
  "bottle_type": null,
  "perprice": 41.5,
  "caseprice": null,
  "bbox": "{\"type\":\"Polygon\",\"coordinates\":[[[1963,-2605],[1963,-2570],[3603,-2570],[3603,-2605],[1963,-2605]]]}",
  "title": "Exciting Wine News from Burgundy 1961",
  "publisher": "Sherry Wine & Spirits Co.,Inc.",
  "publication_date": 1961
}
