{
  "page_ark": "d7pw89-002",
  "ark": "d7pw89",
  "page": 2,
  "name": "SAINT VERAN Cave de Prisse",
  "year_published": 1979,
  "vintage": 1977,
  "type": "wine",
  "color": null,
  "country": "France",
  "section": null,
  "bottle_type": null,
  "perprice": 5.15,
  "caseprice": 59.95,
  "bbox": "{\"type\":\"Polygon\",\"coordinates\":[[[266,-2315],[266,-2277],[2632,-2277],[2632,-2315],[266,-2315]]]}",
  "title": "August 1979: An Historic Wine Event is Now Taking Place...",
  "publisher": "Sherry Wine & Spirits Co.,Inc.",
  "publication_date": 1979
}
{
  "page_ark": "d7pw89-003",
  "ark": "d7pw89",
  "page": 3,
  "name": "PIESPORTER GOLDTROPFCHEN RIESLING QBA Zentralkellerei",
  "year_published": 1979,
  "vintage": null,
  "type": "wine",
  "color": null,
  "country": "US",
  "section": null,
  "bottle_type": null,
  "perprice": 3.99,
  "caseprice": 46.75,
  "bbox": "{\"type\":\"Polygon\",\"coordinates\":[[[309,-1531],[309,-1493],[2653,-1493],[2653,-1531],[309,-1531]]]}",
  "title": "August 1979: An Historic Wine Event is Now Taking Place...",
  "publisher": "Sherry Wine & Spirits Co.,Inc.",
  "publication_date": 1979
}
{
  "page_ark": "d7pw89-003",
  "ark": "d7pw89",
  "page": 3,
  "name": "BERNKASTELER BADSTUBE RIESLING Prum",
  "year_published": 1979,
  "vintage": null,
  "type": "wine",
  "color": null,
  "country": null,
  "section": null,
  "bottle_type": null,
  "perprice": 3.99,
  "caseprice": 46.75,
  "bbox": "{\"type\":\"Polygon\",\"coordinates\":[[[311,-1811],[311,-1772],[2652,-1772],[2652,-1811],[311,-1811]]]}",
  "title": "August 1979: An Historic Wine Event is Now Taking Place...",
  "publisher": "Sherry Wine & Spirits Co.,Inc.",
  "publication_date": 1979
}
{
  "page_ark": "d7pw89-001",
  "ark": "d7pw89",
  "page": 1,
  "name": "ROMANEE SAINT VIVANT",
  "year_published": 1979,
  "vintage": 1976,
  "type": "wine",
  "color": null,
  "country": "France",
  "section": null,
  "bottle_type": null,
  "perprice": 80,
  "caseprice": 912,
  "bbox": "{\"type\":\"Polygon\",\"coordinates\":[[[363,-2835],[363,-2797],[1747,-2797],[1747,-2835],[363,-2835]]]}",
  "title": "August 1979: An Historic Wine Event is Now Taking Place...",
  "publisher": "Sherry Wine & Spirits Co.,Inc.",
  "publication_date": 1979
}
{
  "page_ark": "d7pw89-002",
  "ark": "d7pw89",
  "page": 2,
  "name": "CHIANTI CLASSICO MONTEPALDI Marchese Corsini",
  "year_published": 1979,
  "vintage": 1977,
  "type": "wine",
  "color": null,
  "country": null,
  "section": null,
  "bottle_type": null,
  "perprice": 2.99,
  "caseprice": 35.75,
  "bbox": "{\"type\":\"Polygon\",\"coordinates\":[[[269,-3155],[269,-3117],[2634,-3117],[2634,-3155],[269,-3155]]]}",
  "title": "August 1979: An Historic Wine Event is Now Taking Place...",
  "publisher": "Sherry Wine & Spirits Co.,Inc.",
  "publication_date": 1979
}
{
  "page_ark": "d7pw89-002",
  "ark": "d7pw89",
  "page": 2,
  "name": "BEAUJOLAIS VILLAGES",
  "year_published": 1979,
  "vintage": 1978,
  "type": "wine",
  "color": null,
  "country": "France",
  "section": null,
  "bottle_type": null,
  "perprice": 4.49,
  "caseprice": 49.95,
  "bbox": "{\"type\":\"Polygon\",\"coordinates\":[[[3141,-736],[3141,-697],[5508,-697],[5508,-736],[3141,-736]]]}",
  "title": "August 1979: An Historic Wine Event is Now Taking Place...",
  "publisher": "Sherry Wine & Spirits Co.,Inc.",
  "publication_date": 1979
}
{
  "page_ark": "d7pw89-003",
  "ark": "d7pw89",
  "page": 3,
  "name": "ZELTINGER HIMMELREICH TROCKEN KABIMETT Zentralkellerai",
  "year_published": 1979,
  "vintage": null,
  "type": "wine",
  "color": null,
  "country": "US",
  "section": null,
  "bottle_type": null,
  "perprice": 3.99,
  "caseprice": 46.75,
  "bbox": "{\"type\":\"Polygon\",\"coordinates\":[[[311,-2034],[311,-1995],[2651,-1995],[2651,-2034],[311,-2034]]]}",
  "title": "August 1979: An Historic Wine Event is Now Taking Place...",
  "publisher": "Sherry Wine & Spirits Co.,Inc.",
  "publication_date": 1979
}
{
  "page_ark": "d7pw89-002",
  "ark": "d7pw89",
  "page": 2,
  "name": "CHATEAU ROUSSET (Cotes de Bourg)",
  "year_published": 1979,
  "vintage": 1973,
  "type": "wine",
  "color": null,
  "country": "France",
  "section": null,
  "bottle_type": null,
  "perprice": 2.99,
  "caseprice": 35.75,
  "bbox": "{\"type\":\"Polygon\",\"coordinates\":[[[263,-461],[263,-423],[2630,-423],[2630,-461],[263,-461]]]}",
  "title": "August 1979: An Historic Wine Event is Now Taking Place...",
  "publisher": "Sherry Wine & Spirits Co.,Inc.",
  "publication_date": 1979
}
{
  "page_ark": "d7pw89-002",
  "ark": "d7pw89",
  "page": 2,
  "name": "(ier CLER'BLANC",
  "year_published": 1979,
  "vintage": null,
  "type": "wine",
  "color": "white",
  "country": null,
  "section": null,
  "bottle_type": null,
  "perprice": 2.99,
  "caseprice": 35.75,
  "bbox": "{\"type\":\"Polygon\",\"coordinates\":[[[3126,-2298],[3126,-2259],[5494,-2259],[5494,-2298],[3126,-2298]]]}",
  "title": "August 1979: An Historic Wine Event is Now Taking Place...",
  "publisher": "Sherry Wine & Spirits Co.,Inc.",
  "publication_date": 1979
}
{
  "page_ark": "d7pw89-001",
  "ark": "d7pw89",
  "page": 1,
  "name": "TACHE",
  "year_published": 1979,
  "vintage": 1976,
  "type": "wine",
  "color": null,
  "country": null,
  "section": null,
  "bottle_type": null,
  "perprice": 90,
  "caseprice": 1026,
  "bbox": "{\"type\":\"Polygon\",\"coordinates\":[[[363,-3002],[363,-2965],[1745,-2965],[1745,-3002],[363,-3002]]]}",
  "title": "August 1979: An Historic Wine Event is Now Taking Place...",
  "publisher": "Sherry Wine & Spirits Co.,Inc.",
  "publication_date": 1979
}
{
  "page_ark": "d7pw89-002",
  "ark": "d7pw89",
  "page": 2,
  "name": "FLEURIE",
  "year_published": 1979,
  "vintage": 1978,
  "type": "wine",
  "color": null,
  "country": "France",
  "section": null,
  "bottle_type": null,
  "perprice": 6.29,
  "caseprice": 72.95,
  "bbox": "{\"type\":\"Polygon\",\"coordinates\":[[[3129,-1285],[3129,-1247],[5499,-1247],[5499,-1285],[3129,-1285]]]}",
  "title": "August 1979: An Historic Wine Event is Now Taking Place...",
  "publisher": "Sherry Wine & Spirits Co.,Inc.",
  "publication_date": 1979
}
{
  "page_ark": "d7pw89-001",
  "ark": "d7pw89",
  "page": 1,
  "name": "ROMANEE CONTI",
  "year_published": 1979,
  "vintage": 1976,
  "type": "wine",
  "color": null,
  "country": null,
  "section": null,
  "bottle_type": null,
  "perprice": 150,
  "caseprice": null,
  "bbox": "{\"type\":\"Polygon\",\"coordinates\":[[[362,-3086],[362,-3050],[1437,-3050],[1437,-3086],[362,-3086]]]}",
  "title": "August 1979: An Historic Wine Event is Now Taking Place...",
  "publisher": "Sherry Wine & Spirits Co.,Inc.",
  "publication_date": 1979
}
{
  "page_ark": "d7pw89-002",
  "ark": "d7pw89",
  "page": 2,
  "name": "GROS PLANT SUR LIE CUVEE SEIGNEUR",
  "year_published": 1979,
  "vintage": 1978,
  "type": "wine",
  "color": null,
  "country": null,
  "section": null,
  "bottle_type": null,
  "perprice": 2.99,
  "caseprice": 35.75,
  "bbox": "{\"type\":\"Polygon\",\"coordinates\":[[[3127,-2744],[3127,-2706],[5493,-2706],[5493,-2744],[3127,-2744]]]}",
  "title": "August 1979: An Historic Wine Event is Now Taking Place...",
  "publisher": "Sherry Wine & Spirits Co.,Inc.",
  "publication_date": 1979
}
{
  "page_ark": "d7pw89-002",
  "ark": "d7pw89",
  "page": 2,
  "name": "MUSCADET SUR LIE NOBLERAIE",
  "year_published": 1979,
  "vintage": 1978,
  "type": "wine",
  "color": null,
  "country": "France",
  "section": null,
  "bottle_type": null,
  "perprice": 3.99,
  "caseprice": 47.75,
  "bbox": "{\"type\":\"Polygon\",\"coordinates\":[[[3126,-2963],[3126,-2929],[5489,-2929],[5489,-2963],[3126,-2963]]]}",
  "title": "August 1979: An Historic Wine Event is Now Taking Place...",
  "publisher": "Sherry Wine & Spirits Co.,Inc.",
  "publication_date": 1979
}
{
  "page_ark": "d7pw89-001",
  "ark": "d7pw89",
  "page": 1,
  "name": "RICHEBOURG",
  "year_published": 1979,
  "vintage": 1976,
  "type": "wine",
  "color": null,
  "country": null,
  "section": null,
  "bottle_type": null,
  "perprice": 90,
  "caseprice": 1026,
  "bbox": "{\"type\":\"Polygon\",\"coordinates\":[[[362,-2918],[362,-2880],[1745,-2880],[1745,-2918],[362,-2918]]]}",
  "title": "August 1979: An Historic Wine Event is Now Taking Place...",
  "publisher": "Sherry Wine & Spirits Co.,Inc.",
  "publication_date": 1979
}
{
  "page_ark": "d7pw89-001",
  "ark": "d7pw89",
  "page": 1,
  "name": "ECHEZEAUX",
  "year_published": 1979,
  "vintage": 1976,
  "type": "wine",
  "color": null,
  "country": "France",
  "section": null,
  "bottle_type": null,
  "perprice": 50,
  "caseprice": 570,
  "bbox": "{\"type\":\"Polygon\",\"coordinates\":[[[363,-2666],[363,-2630],[1750,-2630],[1750,-2666],[363,-2666]]]}",
  "title": "August 1979: An Historic Wine Event is Now Taking Place...",
  "publisher": "Sherry Wine & Spirits Co.,Inc.",
  "publication_date": 1979
}
{
  "page_ark": "d7pw89-002",
  "ark": "d7pw89",
  "page": 2,
  "name": "BIANCO TOSCANO MONTEPALDI Marchese Corsini",
  "year_published": 1979,
  "vintage": 1977,
  "type": "wine",
  "color": null,
  "country": null,
  "section": null,
  "bottle_type": null,
  "perprice": 2.99,
  "caseprice": 35.75,
  "bbox": "{\"type\":\"Polygon\",\"coordinates\":[[[269,-3380],[269,-3342],[2634,-3342],[2634,-3380],[269,-3380]]]}",
  "title": "August 1979: An Historic Wine Event is Now Taking Place...",
  "publisher": "Sherry Wine & Spirits Co.,Inc.",
  "publication_date": 1979
}
{
  "page_ark": "d7pw89-003",
  "ark": "d7pw89",
  "page": 3,
  "name": "VIEILLE FERME BLANC DE BLANCS",
  "year_published": 1979,
  "vintage": null,
  "type": "wine",
  "color": "white",
  "country": "France",
  "section": null,
  "bottle_type": null,
  "perprice": 2.99,
  "caseprice": 35.75,
  "bbox": "{\"type\":\"Polygon\",\"coordinates\":[[[311,-772],[311,-735],[2656,-735],[2656,-772],[311,-772]]]}",
  "title": "August 1979: An Historic Wine Event is Now Taking Place...",
  "publisher": "Sherry Wine & Spirits Co.,Inc.",
  "publication_date": 1979
}
{
  "page_ark": "d7pw89-001",
  "ark": "d7pw89",
  "page": 1,
  "name": "GRANDS ECHEZEAUX",
  "year_published": 1979,
  "vintage": 1976,
  "type": "wine",
  "color": null,
  "country": "France",
  "section": null,
  "bottle_type": null,
  "perprice": 70,
  "caseprice": 798,
  "bbox": "{\"type\":\"Polygon\",\"coordinates\":[[[363,-2750],[363,-2713],[1747,-2713],[1747,-2750],[363,-2750]]]}",
  "title": "August 1979: An Historic Wine Event is Now Taking Place...",
  "publisher": "Sherry Wine & Spirits Co.,Inc.",
  "publication_date": 1979
}
{
  "page_ark": "d7pw89-002",
  "ark": "d7pw89",
  "page": 2,
  "name": "MOULIN VENT",
  "year_published": 1979,
  "vintage": 1978,
  "type": "wine",
  "color": null,
  "country": "France",
  "section": null,
  "bottle_type": null,
  "perprice": 6.99,
  "caseprice": 79.95,
  "bbox": "{\"type\":\"Polygon\",\"coordinates\":[[[3127,-1789],[3127,-1753],[5495,-1753],[5495,-1789],[3127,-1789]]]}",
  "title": "August 1979: An Historic Wine Event is Now Taking Place...",
  "publisher": "Sherry Wine & Spirits Co.,Inc.",
  "publication_date": 1979
}
{
  "page_ark": "d7pw89-003",
  "ark": "d7pw89",
  "page": 3,
  "name": "OCKFENER BOCKSTEIN KABINETT Zentralkellerai",
  "year_published": 1979,
  "vintage": null,
  "type": "wine",
  "color": null,
  "country": "US",
  "section": null,
  "bottle_type": null,
  "perprice": 4.99,
  "caseprice": 58.5,
  "bbox": "{\"type\":\"Polygon\",\"coordinates\":[[[310,-2258],[310,-2220],[2652,-2220],[2652,-2258],[310,-2258]]]}",
  "title": "August 1979: An Historic Wine Event is Now Taking Place...",
  "publisher": "Sherry Wine & Spirits Co.,Inc.",
  "publication_date": 1979
}
{
  "page_ark": "d7pw89-002",
  "ark": "d7pw89",
  "page": 2,
  "name": "JULIENAS",
  "year_published": 1979,
  "vintage": 1978,
  "type": "wine",
  "color": null,
  "country": "France",
  "section": null,
  "bottle_type": null,
  "perprice": 6.29,
  "caseprice": 72.95,
  "bbox": "{\"type\":\"Polygon\",\"coordinates\":[[[3126,-1565],[3126,-1528],[5496,-1528],[5496,-1565],[3126,-1565]]]}",
  "title": "August 1979: An Historic Wine Event is Now Taking Place...",
  "publisher": "Sherry Wine & Spirits Co.,Inc.",
  "publication_date": 1979
}
{
  "page_ark": "d7pw89-002",
  "ark": "d7pw89",
  "page": 2,
  "name": "MACON VILLAGES",
  "year_published": 1979,
  "vintage": 1977,
  "type": "wine",
  "color": null,
  "country": null,
  "section": null,
  "bottle_type": null,
  "perprice": 4.49,
  "caseprice": 51.95,
  "bbox": "{\"type\":\"Polygon\",\"coordinates\":[[[268,-1809],[268,-1771],[2632,-1771],[2632,-1809],[268,-1809]]]}",
  "title": "August 1979: An Historic Wine Event is Now Taking Place...",
  "publisher": "Sherry Wine & Spirits Co.,Inc.",
  "publication_date": 1979
}
{
  "page_ark": "d7pw89-002",
  "ark": "d7pw89",
  "page": 2,
  "name": "CHATEAU DES TROIS CANONS (Saint Julien)",
  "year_published": 1979,
  "vintage": 1973,
  "type": "wine",
  "color": null,
  "country": "US",
  "section": null,
  "bottle_type": null,
  "perprice": 4.99,
  "caseprice": 58.5,
  "bbox": "{\"type\":\"Polygon\",\"coordinates\":[[[261,-1138],[261,-1098],[2630,-1098],[2630,-1138],[261,-1138]]]}",
  "title": "August 1979: An Historic Wine Event is Now Taking Place...",
  "publisher": "Sherry Wine & Spirits Co.,Inc.",
  "publication_date": 1979
}
